MANIFEST.in
README.rst
pymaging_psd.py
setup.py
pymaging_psd.egg-info/PKG-INFO
pymaging_psd.egg-info/SOURCES.txt
pymaging_psd.egg-info/dependency_links.txt
pymaging_psd.egg-info/entry_points.txt
pymaging_psd.egg-info/requires.txt
pymaging_psd.egg-info/top_level.txt